{
  "success": true,
  "run_id": "kpi-v3-b-opt-01",
  "request_id": "kpi-v3-b-opt-01",
  "page_id": "327805",
  "flow": "optimized",
  "pattern": "B",
  "edit_intent_hash": "kpi-b-pair-1",
  "scope_selectors": [
    "heading:Overview"
  ],
  "scope_resolution_failed": false,
  "full_page_fetch": false,
  "full_page_adf_bytes": 1841,
  "scoped_adf_bytes": 173,
  "context_reduction_ratio": 0.9060293318848451,
  "pipeline_version": "v1",
  "git_commit_sha": "959755ca323504d5cba8820cc990dc9753b7fceb",
  "git_dirty": true,
  "runtime_mode": "live",
  "state_token_usage": {
    "adf_table_edit": 52,
    "classify": 944,
    "extract_prose": 111,
    "fetch": 1002,
    "md_assist_edit": 114,
    "merge_candidates": 43,
    "patch": 531,
    "publish": 58,
    "verify": 49
  },
  "total_tokens": 2904,
  "retry_count": 0,
  "retry_tokens": 0,
  "patch_ops_bytes": 103,
  "verify_result": "pass",
  "verify_error_codes": [],
  "publish_result": "published",
  "publish_error_code": null,
  "new_version": 5,
  "start_ts": "1970-01-01T00:00:00Z",
  "verify_end_ts": "1970-01-01T00:00:00Z+481ms",
  "publish_end_ts": "1970-01-01T00:00:00Z+1801ms",
  "latency_ms": 1801,
  "locked_node_mutation": false,
  "out_of_scope_mutation": false,
  "telemetry_complete": true,
  "discovered_target_path": "/content/1/content/0/text",
  "applied_paths": [
    "/content/1/content/0/text"
  ],
  "blocked_paths": [],
  "error_codes": [],
  "token_metrics": {
    "adf_table_edit": 52,
    "classify": 944,
    "extract_prose": 111,
    "fetch": 1002,
    "md_assist_edit": 114,
    "merge_candidates": 43,
    "patch": 531,
    "publish": 58,
    "verify": 49
  },
  "failure_state": null,
  "empty_page_detected": false,
  "bootstrap_applied": false
}