{
  "request_id": "kpi-v4-c-opt-03",
  "page_id": "327877",
  "state": "classify",
  "timestamp": "1970-01-01T00:00:00Z",
  "payload": {
    "scoped_adf": {
      "content": [
        {
          "attrs": {
            "level": 2
          },
          "content": [
            {
              "text": "Context",
              "type": "text"
            }
          ],
          "type": "heading"
        },
        {
          "content": [
            {
              "text": "KPI-v4 baseline C3 prose update",
              "type": "text"
            }
          ],
          "type": "paragraph"
        },
        {
          "attrs": {
            "title": "Hidden Details"
          },
          "content": [
            {
              "content": [
                {
                  "text": "Expandable details remain structurally locked.",
                  "type": "text"
                }
              ],
              "type": "paragraph"
            }
          ],
          "type": "expand"
        },
        {
          "attrs": {
            "level": 2
          },
          "content": [
            {
              "text": "Notes",
              "type": "text"
            }
          ],
          "type": "heading"
        },
        {
          "content": [
            {
              "text": "KPI-v4 optimized C2 scoped prose update",
              "type": "text"
            }
          ],
          "type": "paragraph"
        },
        {
          "attrs": {
            "panelType": "info"
          },
          "content": [
            {
              "content": [
                {
                  "text": "Panel content simulates locked-adjacent structure.",
                  "type": "text"
                }
              ],
              "type": "paragraph"
            }
          ],
          "type": "panel"
        },
        {
          "attrs": {
            "level": 2
          },
          "content": [
            {
              "text": "References",
              "type": "text"
            }
          ],
          "type": "heading"
        },
        {
          "content": [
            {
              "text": "KPI-v4 optimized C3 scoped prose update",
              "type": "text"
            }
          ],
          "type": "paragraph"
        },
        {
          "type": "rule"
        }
      ],
      "type": "doc",
      "version": 1
    }
  }
}